st_vizzu/__init__.py
st_vizzu/version.py
st_vizzu-0.1.dist-info/LICENSE
st_vizzu-0.1.dist-info/METADATA
st_vizzu-0.1.dist-info/WHEEL
st_vizzu-0.1.dist-info/top_level.txt
st_vizzu-0.1.dist-info/RECORD
