Metadata-Version: 2.1
Name: st-vizzu
Version: 0.1
Summary: ipyvizzu wrapper for intuitive usage with Streamlt embed support.
Home-page: https://github.com/avrabyt/Streamlit-ipyvizzu
Author: Avratanu Biswas
Author-email: avrab.yt@gmail.com
Requires-Python: >=3.6
License-File: LICENSE
Requires-Dist: streamlit (>=0.63)
Requires-Dist: ipyvizzu
Requires-Dist: pandas
